ALU.v
`define AND   4'b0000
`define OR    4'b0001
`define ADD   4'b0010
`define SUB   4'b0110
`define PassB 4'b0111

module ALU(BusW, BusA, BusB, ALUCtrl, Zero);
    
    output  [63:0] BusW;
    input   [63:0] BusA, BusB;
    input   [3:0] ALUCtrl;
    output  Zero;
    
    reg     [63:0] BusW;
    
    always @(ALUCtrl or BusA or BusB) begin
        case (ALUCtrl)
            `AND:    BusW = BusA & BusB;  // AND
            `OR:     BusW = BusA | BusB;  // ORR
            `ADD:    BusW = BusA + BusB;  // ADD, LDUR/STUR
            `SUB:    BusW = BusA - BusB;  // SUB
            `PassB:  BusW = BusB;         // PassB for CBZ
            default: BusW = 64'b0;
        endcase
    end

    assign Zero = (BusW == 64'd0);

endmodule

RegisterFile.v
module RegisterFile(BusA, BusB, BusW, RA, RB, RW, RegWr, Clk);
    output [63:0] BusA;
    output [63:0] BusB;
    input  [63:0] BusW;
    input  [4:0]  RA; // these need to be 5 bits
    input  [4:0]  RB; // to accomodate for 32
    input  [4:0]  RW; // possible registers
    input  RegWr;
    input  Clk;

    // declare 32, 64-bit registers
    reg [63:0] registers [31:0];
     
    // always return 0 when reading XZR
    // otherwise write to the corresponding register
    assign #2 BusA = (RA == 5'd31) ? 64'b0 : registers[RA];
    assign #2 BusB = (RB == 5'd31) ? 64'b0 : registers[RB];
     
    always @ (negedge Clk) begin
        // prevent write to XZR
        if (RegWr && (RW != 5'd31))
            registers[RW] <= #3 BusW;
    end
endmodule

DataMemory.v
`timescale 1ns / 1ps
`define SIZE 1024

module DataMemory(ReadData , Address , WriteData , MemoryRead , MemoryWrite , Clock);
	input      [63:0] WriteData;
	input      [63:0] Address;
	input             Clock, MemoryRead, MemoryWrite;
	output reg [63:0] ReadData;

	reg        [7:0]  memBank [`SIZE-1:0];


	// This task is used to write arbitrary data to the Data Memory by
	// the intialization block.
	task initset;
		input [63:0] addr;
    	input [63:0] data;
    	begin
			memBank[addr] =  data[63:56] ; // Big-endian for the win...
			memBank[addr+1] =  data[55:48];
			memBank[addr+2] =  data[47:40];
			memBank[addr+3] =  data[39:32];
			memBank[addr+4] =  data[31:24];
			memBank[addr+5] =  data[23:16];
			memBank[addr+6] =  data[15:8];
			memBank[addr+7] =  data[7:0];
    	end
    endtask


	initial begin
        // preseting some data in the data memory used by test #1

        // Address 0x0 gets 0x1
    	initset( 64'h0,  64'h1);  //Counter variable
        initset( 64'h8,  64'ha);  //Part of mask
        initset( 64'h10, 64'h5);  //Other part of mask
        initset( 64'h18, 64'h0ffbea7deadbeeff); //big constant
        initset( 64'h20, 64'h0); //clearing space

        // Add any data you need for your tests here.

    end

	// This always block reads the data memory and places a double word
	// on the ReadData bus.
	always @(posedge Clock) begin
        if(MemoryRead) begin
            ReadData[63:56] <=  memBank[Address];
            ReadData[55:48] <=  memBank[Address+1];
            ReadData[47:40] <=  memBank[Address+2];
            ReadData[39:32] <=  memBank[Address+3];
            ReadData[31:24] <=  memBank[Address+4];
            ReadData[23:16] <=  memBank[Address+5];
            ReadData[15:8] <=  memBank[Address+6];
            ReadData[7:0] <=  memBank[Address+7];
        end
    end

   // This always block takes data from the WriteData bus and writes
   // it into the DataMemory.
    always @(posedge Clock) begin
        if(MemoryWrite) begin
            memBank[Address] <= #3 WriteData[63:56] ;
            memBank[Address+1] <= #3 WriteData[55:48];
            memBank[Address+2] <= #3 WriteData[47:40];
            memBank[Address+3] <= #3 WriteData[39:32];
            memBank[Address+4] <= #3 WriteData[31:24];
            memBank[Address+5] <= #3 WriteData[23:16];
            memBank[Address+6] <= #3 WriteData[15:8];
            memBank[Address+7] <= #3 WriteData[7:0];
            // Could be useful for debugging:
            // $display("Writing Address:%h Data:%h",Address, WriteData);
        end
    end
endmodule

NextPClogic.v
module NextPClogic(NextPC, CurrentPC, SignExtImm64, Branch, ALUZero, Uncondbranch); 
	input [63:0] CurrentPC, SignExtImm64; 
	input Branch, ALUZero, Uncondbranch; 
	output [63:0] NextPC; 

	// if the instruction is an unconditional branch, we should jump to the branch target
	// we should also do this if the instruction is conditional and true
	// otherwise, we should just increment the PC by 4
	assign NextPC = (Uncondbranch | (Branch & ALUZero)) ? (CurrentPC + (SignExtImm64 << 2)) : (CurrentPC + 64'd4);

endmodule

SignExtender.v
module SignExtender(
	output reg [63:0] imm64,
	input [25:0] instr,
	input [2:0]  ctrl   // need to handle MOVZ
); 

	wire [11:0] imm12 = instr[21:10]; // I-type
	wire [8:0]  imm9  = instr[20:12]; // D-type
	wire [25:0] imm26 = instr[25:0];  // B-type
	wire [18:0] imm19 = instr[23:5];  // CB-type
   
	always @(*) begin
		case (ctrl)
			// I-type: zero-extend (since immediate is always unsigned)
			3'b000:   imm64 = {52'b0, imm12};
			// D-type: sign-extend
			3'b001:   imm64 = {{55{imm9[8]}}, imm9};
			// B-type: sign-extend
			3'b010:   imm64 = {{38{imm26[25]}}, imm26};
			// CB-type: sign-extend
			3'b011:   imm64 = {{45{imm19[18]}}, imm19};
			// MOVZ
			3'b100:
            begin
                case(instr[22:21]) // halfword selector bits
                    2'b00: 		   // shift 2^0
                        imm64 = {48'b0, instr[20:5]};
                    2'b01:         // shift 2^16
                        imm64 = {32'b0, instr[20:5], 16'b0};
                    2'b10:         // shift 2^32
                        imm64 = {16'b0, instr[20:5], 32'b0};
                    2'b11:         // shift 2^48
                        imm64 = {instr[20:5], 48'b0};
					
					default: imm64 = 64'b0;
                endcase
            end

			default: imm64 = 64'b0;
		endcase
	end
endmodule

SingleCycleControl.v
`define OPCODE_ANDREG 11'b?0001010???
`define OPCODE_ORRREG 11'b?0101010???
`define OPCODE_ADDREG 11'b?0?01011???
`define OPCODE_SUBREG 11'b?1?01011???

`define OPCODE_ADDIMM 11'b?0?10001???
`define OPCODE_SUBIMM 11'b?1?10001???

`define OPCODE_MOVZ   11'b110100101??

`define OPCODE_B      11'b?00101?????
`define OPCODE_CBZ    11'b?011010????

`define OPCODE_LDUR   11'b??111000010
`define OPCODE_STUR   11'b??111000000

module control(
	output reg 	   reg2loc,
	output reg 	   alusrc,
	output reg 	   mem2reg,
	output reg 	   regwrite,
	output reg 	   memread,
	output reg 	   memwrite,
	output reg 	   branch,	
	output reg 	   uncond_branch,
	output reg [3:0]  aluop,
	output reg [2:0]  signop,
	input      [10:0] opcode
);

     always @(*) begin
	     casez (opcode)
               `OPCODE_ANDREG:
               begin
                    reg2loc       <= 1'b0;
                    alusrc        <= 1'b0;
                    mem2reg       <= 1'b0;
                    regwrite      <= 1'b1;
                    memread       <= 1'b0;
                    memwrite      <= 1'b0;
                    branch        <= 1'b0;
                    uncond_branch <= 1'b0;
                    aluop         <= 4'b0000;
                    signop        <= 3'bxxx;
               end

               `OPCODE_ORRREG:
               begin
                    reg2loc       <= 1'b0;
                    alusrc        <= 1'b0;
                    mem2reg       <= 1'b0;
                    regwrite      <= 1'b1;
                    memread       <= 1'b0;
                    memwrite      <= 1'b0;
                    branch        <= 1'b0;
                    uncond_branch <= 1'b0;
                    aluop         <= 4'b0001;
                    signop        <= 3'bxxx;
               end

               `OPCODE_ADDREG:
               begin
                    reg2loc       <= 1'b0;
                    alusrc        <= 1'b0;
                    mem2reg       <= 1'b0;
                    regwrite      <= 1'b1;
                    memread       <= 1'b0;
                    memwrite      <= 1'b0;
                    branch        <= 1'b0;
                    uncond_branch <= 1'b0;
                    aluop         <= 4'b0010;
                    signop        <= 3'bxxx;
               end

               `OPCODE_SUBREG:
               begin
                    reg2loc       <= 1'b0;
                    alusrc        <= 1'b0;
                    mem2reg       <= 1'b0;
                    regwrite      <= 1'b1;
                    memread       <= 1'b0;
                    memwrite      <= 1'b0;
                    branch        <= 1'b0;
                    uncond_branch <= 1'b0;
                    aluop         <= 4'b0110;
                    signop        <= 3'bxxx;
               end

               `OPCODE_ADDIMM:
               begin
                    reg2loc       <= 1'bx;
                    alusrc        <= 1'b1;
                    mem2reg       <= 1'b0;
                    regwrite      <= 1'b1;
                    memread       <= 1'b0;
                    memwrite      <= 1'b0;
                    branch        <= 1'b0;
                    uncond_branch <= 1'b0;
                    aluop         <= 4'b0010;
                    signop        <= 3'b000;
               end

               `OPCODE_SUBIMM:
               begin
                    reg2loc       <= 1'bx;
                    alusrc        <= 1'b1;
                    mem2reg       <= 1'b0;
                    regwrite      <= 1'b1;
                    memread       <= 1'b0;
                    memwrite      <= 1'b0;
                    branch        <= 1'b0;
                    uncond_branch <= 1'b0;
                    aluop         <= 4'b0110;
                    signop        <= 3'b000;
               end

               `OPCODE_MOVZ:
               begin
                    reg2loc       <= 1'bx;
                    alusrc        <= 1'b1;
                    mem2reg       <= 1'b0;
                    regwrite      <= 1'b1;
                    memread       <= 1'b0;
                    memwrite      <= 1'b0;
                    branch        <= 1'b0;
                    uncond_branch <= 1'b0;
                    aluop         <= 4'b0111;
                    signop        <= 3'b100;
               end

               `OPCODE_B:
               begin
                    reg2loc       <= 1'bx;
                    alusrc        <= 1'bx;
                    mem2reg       <= 1'bx;
                    regwrite      <= 1'b0;
                    memread       <= 1'b0;
                    memwrite      <= 1'b0;
                    branch        <= 1'b0;
                    uncond_branch <= 1'b1;
                    aluop         <= 4'bxxxx;
                    signop        <= 3'b010;
               end
               
               `OPCODE_CBZ:
               begin
                    reg2loc       <= 1'b1;
                    alusrc        <= 1'b0;
                    mem2reg       <= 1'bx;
                    regwrite      <= 1'b0;
                    memread       <= 1'b0;
                    memwrite      <= 1'b0;
                    branch        <= 1'b1;
                    uncond_branch <= 1'b0;
                    aluop         <= 4'b0111;
                    signop        <= 3'b011;
               end

               `OPCODE_LDUR:
               begin
                    reg2loc       <= 1'bx;
                    alusrc        <= 1'b1;
                    mem2reg       <= 1'b1;
                    regwrite      <= 1'b1;
                    memread       <= 1'b1;
                    memwrite      <= 1'b0;
                    branch        <= 1'b0;
                    uncond_branch <= 1'b0;
                    aluop         <= 4'b0010;
                    signop        <= 3'b001;
               end

               `OPCODE_STUR:
               begin
                    reg2loc       <= 1'b1;
                    alusrc        <= 1'b1;
                    mem2reg       <= 1'b0;
                    regwrite      <= 1'b0;
                    memread       <= 1'b0;
                    memwrite      <= 1'b1;
                    branch        <= 1'b0;
                    uncond_branch <= 1'b0;
                    aluop         <= 4'b0010;
                    signop        <= 3'b001;
               end

               default:
               begin
                    reg2loc       <= 1'bx;
                    alusrc        <= 1'bx;
                    mem2reg       <= 1'bx;
                    regwrite      <= 1'b0;
                    memread       <= 1'b0;
                    memwrite      <= 1'b0;
                    branch        <= 1'b0;
                    uncond_branch <= 1'b0;
                    aluop         <= 4'bxxxx;
                    signop        <= 3'bxxx;
               end
	     endcase
     end
endmodule

InstructionMemory.v
`timescale 1ns / 1ps
/*
 * Module: InstructionMemory
 *
 * Implements read-only instruction memory
 * 
 */
module InstructionMemory(Data, Address);
	parameter T_rd = 20;
    parameter MemSize = 40;
   
    output [31:0] Data;
    input [63:0]  Address;
    reg [31:0] 	 Data;
   
    /*
    ECEN 350 Processor Test Functions
    Texas A&M University
    */
   
    always @ (Address) begin
    	case(Address)

	/*
	Test Program 1:
	Program loads constants from the data memory. Uses these constants to test
	the following instructions: LDUR, ORR, AND, CBZ, ADD, SUB, STUR and B.
	
	Assembly code for test:
	
	0: LDUR X9, [XZR, 0x0]    //Load 1 into x9
	4: LDUR X10, [XZR, 0x8]   //Load a into x10
	8: LDUR X11, [XZR, 0x10]  //Load 5 into x11
	C: LDUR X12, [XZR, 0x18]  //Load big constant into x12
	10: LDUR X13, [XZR, 0x20]  //load a 0 into X13
	
	14: ORR X10, X10, X11  //Create mask of 0xf
	18: AND X12, X12, X10  //Mask off low order bits of big constant
	
	loop:
	1C: CBZ X12, end  //while X12 is not 0
	20: ADD X13, X13, X9  //Increment counter in X13
	24: SUB X12, X12, X9  //Decrement remainder of big constant in X12
	28: B loop  //Repeat till X12 is 0
	2C: STUR X13, [XZR, 0x20]  //store back the counter value into the memory location 0x20
	*/

	63'h000: Data = 32'hF84003E9;
	63'h004: Data = 32'hF84083EA;
	63'h008: Data = 32'hF84103EB;
	63'h00c: Data = 32'hF84183EC;
	63'h010: Data = 32'hF84203ED;
	63'h014: Data = 32'hAA0B014A;
	63'h018: Data = 32'h8A0A018C;
	63'h01c: Data = 32'hB400008C;
	63'h020: Data = 32'h8B0901AD;
	63'h024: Data = 32'hCB09018C;
	63'h028: Data = 32'h17FFFFFD;
	63'h02c: Data = 32'hF80203ED;
	63'h030: Data = 32'hF84203ED;  //One last load to place stored value on memdbus for test checking.

	/* Add code for your tests here */
	63'h034: Data = 32'b11010010111000100100011010001001; // MOVZ X9,  #0x1234, LSL #48
	63'h038: Data = 32'b11010010110010101100111100001010; // MOVZ X10, #0x5678, LSL #32
	63'h03C: Data = 32'b10101010000010100000000100101001; // ORR  X9, X9, X10
	63'h040: Data = 32'b11010010101100110101011110001010; // MOVZ X10, #0x9ABC, LSL #16
	63'h044: Data = 32'b10101010000010100000000100101001; // ORR  X9, X9, X10
	63'h048: Data = 32'b11010010100110111101111000001010; // MOVZ X10, #0xDEF0
	63'h04C: Data = 32'b10101010000010100000000100101001; // ORR  X9, X9, X10
	63'h050: Data = 32'b11111000000000101000001111101001; // STUR X9,  [X31,#0x28]
	63'h054: Data = 32'b11111000010000101000001111101010; // LDUR X10, [X31,#0x28]
	
	default: Data = 32'hXXXXXXXX;
    	endcase
    end
endmodule

SingleCycleProc.v
module singlecycle(
	input 	          resetl,
	input      [63:0] startpc,
	output reg [63:0] currentpc,
	output     [63:0] MemtoRegOut,  // this should be
				   					// attached to the
				   					// output of the
				   					// MemtoReg Mux
	input CLK
);

    // Next PC connections
	wire [63:0] nextpc;        // The next PC, to be updated on clock cycle

    // Instruction Memory connections
    wire [31:0] instruction;   // The current instruction

    // Parts of instruction
    wire [4:0]  rd;            // The destination register
    wire [4:0]  rm;            // Operand 1
    wire [4:0]  rn;            // Operand 2
    wire [10:0] opcode;

    // Control wires
    wire 	   reg2loc;
    wire 	   alusrc;
    wire 	   mem2reg;
    wire 	   regwrite;
    wire 	   memread;
    wire 	   memwrite;
    wire 	   branch;
    wire 	   uncond_branch;
    wire [3:0] aluctrl;
    wire [2:0] signop;

    // Register file connections
    wire [63:0] regoutA;     // Output A
    wire [63:0] regoutB;     // Output B

    // ALU connections
    wire [63:0] aluout;
    wire 		zero;

    // Sign Extender connections
    wire [63:0] extimm;

    // PC update logic
    always @(negedge CLK) begin
        if (resetl)
            currentpc <= #3 nextpc;
        else
            currentpc <= #3 startpc;
    end

    // Parts of instruction
    assign rd = instruction[4:0];
    assign rm = instruction[9:5];
    assign rn = reg2loc ? instruction[4:0] : instruction[20:16];
    assign opcode = instruction[31:21];

    InstructionMemory imem(
		.Data(instruction),
		.Address(currentpc)
	);

    control control(
		.reg2loc(reg2loc),
		.alusrc(alusrc),
		.mem2reg(mem2reg),
		.regwrite(regwrite),
		.memread(memread),
		.memwrite(memwrite),
		.branch(branch),
		.uncond_branch(uncond_branch),
		.aluop(aluctrl),
		.signop(signop),
		.opcode(opcode)
	);

    /*
    Connect the remaining datapath elements below.
    Do not forget any additional multiplexers that may be required.
    */

    SignExtender SignExtender(
        .imm64(extimm),
        .instr(instruction[25:0]),
        .ctrl(signop)
    );

    NextPClogic NextPClogic(
        .NextPC(nextpc),
        .CurrentPC(currentpc),
        .SignExtImm64(extimm),
        .Branch(branch),
        .ALUZero(zero),
        .Uncondbranch(uncond_branch)
    );

    wire [63:0] dataout;
    DataMemory DataMemory(
        .ReadData(dataout),
        .Address(aluout),
        .WriteData(regoutB),
        .MemoryRead(memread),
        .MemoryWrite(memwrite),
        .Clock(CLK)
    );

    assign MemtoRegOut = mem2reg ? dataout : aluout;
    RegisterFile RegisterFile(
        .BusA(regoutA),
        .BusB(regoutB),
        .BusW(MemtoRegOut),
        .RA(rm),
        .RB(rn),
        .RW(rd),
        .RegWr(regwrite),
        .Clk(CLK)
    );

    wire [63:0] ALUMux;
    assign ALUMux = alusrc ? extimm : regoutB;
    ALU ALU(
        .BusW(aluout),
        .BusA(regoutA),
        .BusB(ALUMux),
        .ALUCtrl(aluctrl),
        .Zero(zero)
    );

endmodule

SingleCycleProcTest.v
`timescale 1ns / 1ps

`define STRLEN 32
`define HalfClockPeriod 60
`define ClockPeriod `HalfClockPeriod * 2

module SingleCycleProcTest_v;

    initial begin
        $dumpfile("singlecycle.vcd");
        $dumpvars;
    end

	// These tasks are used to check if a given test has passed and
    // confirm that all tests passed.
    task passTest;
        input [63:0] actualOut, expectedOut;
        input [`STRLEN*8:0] testType;
        inout [7:0] 	  passed;

        if(actualOut == expectedOut) begin $display ("%s passed", testType); passed = passed + 1; end
        else $display ("%s failed: 0x%x should be 0x%x", testType, actualOut, expectedOut);
    endtask

    task allPassed;
        input [7:0] passed;
        input [7:0] numTests;

        if(passed == numTests) $display ("All tests passed");
        else $display("Some tests failed: %d of %d passed", passed, numTests);
    endtask

    // Inputs
    reg 		  CLK;
    reg 		  Reset_L;
    reg [63:0] 	  startPC;
    reg [7:0] 	  passed;
    reg [15:0] 	  watchdog;

    // Outputs
    wire [63:0] 	  MemtoRegOut;
    wire [63:0] 	  currentPC;

    // Instantiate the Unit Under Test (UUT)
    singlecycle uut (
	 	.CLK(CLK),
	 	.resetl(Reset_L),
	 	.startpc(startPC),
	 	.currentpc(currentPC),
	 	.MemtoRegOut(MemtoRegOut)
	);

    initial begin
		// Initialize Inputs
		Reset_L = 1;
		startPC = 0;
		passed = 0;

		// Initialize Watchdog timer
		watchdog = 0;

		// Wait for global reset
		#(1 * `ClockPeriod);

		// Program 1
		#1
		Reset_L = 0; startPC = 0;
		@(posedge CLK);
		@(negedge CLK);
		@(posedge CLK);
		Reset_L = 1;

		// ***********************************************************
		// This while loop will continue cycling the processor until the
		// PC reaches the final instruction in the first test.  If the
		// program forms an infinite loop, never reaching the end, the
		// watchdog timer will kick in and kill simulation after 64K
		// cycles.
		// ***********************************************************

		while (currentPC < 64'h30) begin
			@(posedge CLK);
			@(negedge CLK);
			$display("CurrentPC:%h",currentPC);
		end
		passTest(MemtoRegOut, 64'hF, "Results of Program 1", passed);

		// ***********************************************************
		// Add your new tests here
		// ***********************************************************
		while (currentPC < 64'h54) begin
  			@(posedge CLK);
  			@(negedge CLK);
			$display("CurrentPC:%h",currentPC);
		end
		passTest(MemtoRegOut, 64'h123456789ABCDEF0, "Results of Program 1 with MOVZ", passed);

		// Done
		allPassed(passed, 2);   // Be sure to change the one to match
		// the number of tests you add.
		$finish;
	end

	// Initialize the clock to be 0
	initial begin
		CLK = 0;
	end

	// The following is correct if clock starts at LOW level at StartTime //
	always begin
		#`HalfClockPeriod CLK = ~CLK;
		#`HalfClockPeriod CLK = ~CLK;
		watchdog = watchdog +1;
	end

	// Kill the simulation if the watchdog hits 64K cycles
	always @*
		if (watchdog == 16'hFF) begin
			$display("Watchdog Timer Expired.");
			$finish;
		end

endmodule

singlecycle.vcd
$date
	Sun Dec 14 01:36:02 2025
$end
$version
	Icarus Verilog
$end
$timescale
	1ps
$end
$scope module SingleCycleProcTest_v $end
$var wire 64 ! currentPC [63:0] $end
$var wire 64 " MemtoRegOut [63:0] $end
$var reg 1 # CLK $end
$var reg 1 $ Reset_L $end
$var reg 8 % passed [7:0] $end
$var reg 64 & startPC [63:0] $end
$var reg 16 ' watchdog [15:0] $end
$scope module uut $end
$var wire 1 # CLK $end
$var wire 1 $ resetl $end
$var wire 64 ( startpc [63:0] $end
$var wire 1 ) zero $end
$var wire 1 * uncond_branch $end
$var wire 3 + signop [2:0] $end
$var wire 5 , rn [4:0] $end
$var wire 5 - rm [4:0] $end
$var wire 1 . regwrite $end
$var wire 64 / regoutB [63:0] $end
$var wire 64 0 regoutA [63:0] $end
$var wire 1 1 reg2loc $end
$var wire 5 2 rd [4:0] $end
$var wire 11 3 opcode [10:0] $end
$var wire 64 4 nextpc [63:0] $end
$var wire 1 5 memwrite $end
$var wire 1 6 memread $end
$var wire 1 7 mem2reg $end
$var wire 32 8 instruction [31:0] $end
$var wire 64 9 extimm [63:0] $end
$var wire 64 : dataout [63:0] $end
$var wire 1 ; branch $end
$var wire 1 < alusrc $end
$var wire 64 = aluout [63:0] $end
$var wire 4 > aluctrl [3:0] $end
$var wire 64 ? MemtoRegOut [63:0] $end
$var wire 64 @ ALUMux [63:0] $end
$var reg 64 A currentpc [63:0] $end
$scope module ALU $end
$var wire 64 B BusB [63:0] $end
$var wire 1 ) Zero $end
$var wire 64 C BusA [63:0] $end
$var wire 4 D ALUCtrl [3:0] $end
$var reg 64 E BusW [63:0] $end
$upscope $end
$scope module DataMemory $end
$var wire 64 F Address [63:0] $end
$var wire 1 # Clock $end
$var wire 64 G WriteData [63:0] $end
$var wire 1 5 MemoryWrite $end
$var wire 1 6 MemoryRead $end
$var reg 64 H ReadData [63:0] $end
$scope task initset $end
$var reg 64 I addr [63:0] $end
$var reg 64 J data [63:0] $end
$upscope $end
$upscope $end
$scope module NextPClogic $end
$var wire 1 ) ALUZero $end
$var wire 64 K CurrentPC [63:0] $end
$var wire 1 * Uncondbranch $end
$var wire 64 L SignExtImm64 [63:0] $end
$var wire 64 M NextPC [63:0] $end
$var wire 1 ; Branch $end
$upscope $end
$scope module RegisterFile $end
$var wire 64 N BusW [63:0] $end
$var wire 1 # Clk $end
$var wire 5 O RA [4:0] $end
$var wire 5 P RB [4:0] $end
$var wire 5 Q RW [4:0] $end
$var wire 1 . RegWr $end
$var wire 64 R BusB [63:0] $end
$var wire 64 S BusA [63:0] $end
$upscope $end
$scope module SignExtender $end
$var wire 26 T imm26 [25:0] $end
$var wire 26 U instr [25:0] $end
$var wire 9 V imm9 [8:0] $end
$var wire 19 W imm19 [18:0] $end
$var wire 12 X imm12 [11:0] $end
$var wire 3 Y ctrl [2:0] $end
$var reg 64 Z imm64 [63:0] $end
$upscope $end
$scope module control $end
$var wire 11 [ opcode [10:0] $end
$var reg 4 \ aluop [3:0] $end
$var reg 1 < alusrc $end
$var reg 1 ; branch $end
$var reg 1 7 mem2reg $end
$var reg 1 6 memread $end
$var reg 1 5 memwrite $end
$var reg 1 1 reg2loc $end
$var reg 1 . regwrite $end
$var reg 3 ] signop [2:0] $end
$var reg 1 * uncond_branch $end
$upscope $end
$scope module imem $end
$var wire 64 ^ Address [63:0] $end
$var reg 32 _ Data [31:0] $end
$upscope $end
$upscope $end
$scope task allPassed $end
$var reg 8 ` numTests [7:0] $end
$var reg 8 a passed [7:0] $end
$upscope $end
$scope task passTest $end
$var reg 64 b actualOut [63:0] $end
$var reg 64 c expectedOut [63:0] $end
$var reg 8 d passed [7:0] $end
$var reg 257 e testType [256:0] $end
$upscope $end
$upscope $end
$enddefinitions $end
#0
$dumpvars
bx e
bx d
bx c
bx b
bx a
bx `
bx _
bx ^
bx ]
bx \
bx [
bx Z
bx Y
bx X
bx W
bx V
bx U
bx T
bx S
bx R
bx Q
bx P
bx O
bx N
bx M
bx L
bx K
b0 J
b100000 I
bx H
bx G
bx F
bx E
bx D
bx C
bx B
bx A
bx @
bx ?
bx >
bx =
x<
x;
bx :
bx 9
bx 8
x7
x6
x5
bx 4
bx 3
bx 2
x1
bx 0
bx /
x.
bx -
bx ,
bx +
x*
x)
b0 (
b0 '
b0 &
b0 %
1$
0#
bx "
bx !
$end
#60000
1#
#120000
b1 '
0#
#121000
0$
#180000
1#
#240000
b10 '
0#
#243000
b0 @
b0 B
b1 +
b1 Y
b1 ]
b10 >
b10 D
b10 \
0*
0;
05
16
1.
17
1<
b100 4
b100 M
b0 9
b0 L
b0 Z
b0 X
b0 V
b100000000000011111 W
b0x00x ,
b0x00x P
b10000000000001111101001 T
b10000000000001111101001 U
b11111000010 3
b11111000010 [
b11111 -
b11111 O
b1001 2
b1001 Q
b11111000010000000000001111101001 8
b11111000010000000000001111101001 _
b0 !
b0 A
b0 K
b0 ^
#245000
1)
b0 =
b0 E
b0 F
b0 0
b0 C
b0 S
#300000
b1 "
b1 ?
b1 N
b1 :
b1 H
1$
1#
#360000
b11 '
0#
#363000
0)
b1000 =
b1000 E
b1000 F
b1000 @
b1000 B
b1000 9
b1000 L
b1000 Z
b100000 X
b1000 V
b100000010000011111 W
b0x0x0 ,
b0x0x0 P
b10000001000001111101010 T
b10000001000001111101010 U
b1010 2
b1010 Q
b1000 4
b1000 M
b11111000010000001000001111101010 8
b11111000010000001000001111101010 _
b100 !
b100 A
b100 K
b100 ^
#420000
b1010 "
b1010 ?
b1010 N
b1010 :
b1010 H
1#
#480000
b100 '
0#
#483000
b10000 =
b10000 E
b10000 F
b10000 @
b10000 B
b10000 9
b10000 L
b10000 Z
b1000000 X
b10000 V
b100000100000011111 W
b0x0x1 ,
b0x0x1 P
b10000010000001111101011 T
b10000010000001111101011 U
b1011 2
b1011 Q
b1100 4
b1100 M
b11111000010000010000001111101011 8
b11111000010000010000001111101011 _
b1000 !
b1000 A
b1000 K
b1000 ^
#540000
b101 "
b101 ?
b101 N
b101 :
b101 H
1#
#600000
b101 '
0#
#603000
b11000 =
b11000 E
b11000 F
b11000 @
b11000 B
b11000 9
b11000 L
b11000 Z
b1100000 X
b11000 V
b100000110000011111 W
b0xx0x ,
b0xx0x P
b10000011000001111101100 T
b10000011000001111101100 U
b1100 2
b1100 Q
b10000 4
b10000 M
b11111000010000011000001111101100 8
b11111000010000011000001111101100 _
b1100 !
b1100 A
b1100 K
b1100 ^
#660000
b111111111011111010100111110111101010110110111110111011111111 "
b111111111011111010100111110111101010110110111110111011111111 ?
b111111111011111010100111110111101010110110111110111011111111 N
b111111111011111010100111110111101010110110111110111011111111 :
b111111111011111010100111110111101010110110111110111011111111 H
1#
#720000
b110 '
0#
#723000
b100000 =
b100000 E
b100000 F
b100000 @
b100000 B
b100000 9
b100000 L
b100000 Z
b10000000 X
b100000 V
b100001000000011111 W
b0xxxx ,
b0xxxx P
b10000100000001111101101 T
b10000100000001111101101 U
b1101 2
b1101 Q
b10100 4
b10100 M
b11111000010000100000001111101101 8
b11111000010000100000001111101101 _
b10000 !
b10000 A
b10000 K
b10000 ^
#780000
b0 "
b0 ?
b0 N
b0 :
b0 H
1#
#840000
b111 '
0#
#843000
x)
bx "
bx ?
bx N
bx +
bx Y
bx ]
b1 >
b1 D
b1 \
06
07
0<
01
bx =
bx E
bx F
bx @
bx B
b0 9
b0 L
b0 Z
b1011000000 X
b10110000 V
b101100000001010 W
b1011 ,
b1011 P
b10000010110000000101001010 T
b10000010110000000101001010 U
b10101010000 3
b10101010000 [
b1010 -
b1010 O
b1010 2
b1010 Q
b11000 4
b11000 M
b10101010000010110000000101001010 8
b10101010000010110000000101001010 _
b10100 !
b10100 A
b10100 K
b10100 ^
#845000
b1111 "
b1111 ?
b1111 N
b101 @
b101 B
0)
b1111 =
b1111 E
b1111 F
b101 /
b101 G
b101 R
b1010 0
b1010 C
b1010 S
#900000
1#
#960000
b1000 '
0#
#963000
b0 "
b0 ?
b0 N
1)
b0 =
b0 E
b0 F
b0 >
b0 D
b0 \
b1010000000 X
b10100000 V
b101000000001100 W
b1010 ,
b1010 P
b10000010100000000110001100 T
b10000010100000000110001100 U
b10001010000 3
b10001010000 [
b1100 -
b1100 O
b1100 2
b1100 Q
b11100 4
b11100 M
b10001010000010100000000110001100 8
b10001010000010100000000110001100 _
b11000 !
b11000 A
b11000 K
b11000 ^
#965000
b1111 "
b1111 ?
b1111 N
b1111 @
b1111 B
0)
b1111 =
b1111 E
b1111 F
b1111 /
b1111 G
b1111 R
b111111111011111010100111110111101010110110111110111011111111 0
b111111111011111010100111110111101010110110111110111011111111 C
b111111111011111010100111110111101010110110111110111011111111 S
#1020000
1#
#1080000
b1001 '
0#
#1083000
b100 9
b100 L
b100 Z
b0xxxx "
b0xxxx ?
b0xxxx N
b11 +
b11 Y
b11 ]
b111 >
b111 D
b111 \
1;
0.
x7
11
b0 X
b0 V
b100 W
b1100 ,
b1100 P
b10001100 T
b10001100 U
b10110100000 3
b10110100000 [
b100 -
b100 O
b100000 4
b100000 M
b10110100000000000000000010001100 8
b10110100000000000000000010001100 _
b11100 !
b11100 A
b11100 K
b11100 ^
#1085000
bx 0
bx C
bx S
#1140000
1#
#1200000
b1010 '
0#
#1203000
x)
bx =
bx E
bx F
bx "
bx ?
bx N
bx +
bx Y
bx ]
b10 >
b10 D
b10 \
0;
1.
07
01
b0 9
b0 L
b0 Z
b1001000000 X
b10010000 V
b100100000001101 W
b1001 ,
b1001 P
b11000010010000000110101101 T
b11000010010000000110101101 U
b10001011000 3
b10001011000 [
b1101 -
b1101 O
b1101 2
b1101 Q
b100100 4
b100100 M
b10001011000010010000000110101101 8
b10001011000010010000000110101101 _
b100000 !
b100000 A
b100000 K
b100000 ^
#1205000
b1 "
b1 ?
b1 N
b1 @
b1 B
0)
b1 =
b1 E
b1 F
b1 /
b1 G
b1 R
b0 0
b0 C
b0 S
#1260000
1#
#1320000
b1011 '
0#
#1323000
b1111111111111111111111111111111111111111111111111111111111111111 "
b1111111111111111111111111111111111111111111111111111111111111111 ?
b1111111111111111111111111111111111111111111111111111111111111111 N
b1111111111111111111111111111111111111111111111111111111111111111 =
b1111111111111111111111111111111111111111111111111111111111111111 E
b1111111111111111111111111111111111111111111111111111111111111111 F
b110 >
b110 D
b110 \
b100100000001100 W
b11000010010000000110001100 T
b11000010010000000110001100 U
b11001011000 3
b11001011000 [
b1100 -
b1100 O
b1100 2
b1100 Q
b101000 4
b101000 M
b11001011000010010000000110001100 8
b11001011000010010000000110001100 _
b100100 !
b100100 A
b100100 K
b100100 ^
#1325000
b1110 "
b1110 ?
b1110 N
b1110 =
b1110 E
b1110 F
b1111 0
b1111 C
b1111 S
#1380000
1#
#1440000
b1100 '
0#
